ppdet
tools
