Metadata-Version: 1.0
Name: ppdet-notebook
Version: 0.4.3.7
Summary: PaddleDetection for notebook
Home-page: https://github.com/PaddlePaddle/PaddleDetection
Author: tianzhi
Author-email: ylj_yanglijuan@163.com
License: UNKNOWN
Platform: UNKNOWN
